{
    "template_info": {
        "id": "10575",
        "name": "GCP Cloud SQL PostgreSQL by HTTP",
        "description": "Get GCP Cloud SQL PostgreSQL instances monitoring with script item usage to perform HTTP requests to Google Cloud Platform Monitoring API.\r\nThis template will be automatically connected to discovered entities with all their required parameters pre-defined.\r\n\r\nYou can discuss this template or leave feedback on our forum https://www.zabbix.com/forum/zabbix-suggestions-and-feedback.\r\n\r\nGenerated by official Zabbix template tool \"Templator\"",
        "total_items": 27
    },
    "items": [
        {
            "itemid": "44966",
            "name": "Reserved CPU cores",
            "key_": "gcp.cloudsql.pgsql.cpu.reserved_cores",
            "delay": "0",
            "type": "18",
            "value_type": "0"
        },
        {
            "itemid": "44979",
            "name": "CPU usage time",
            "key_": "gcp.cloudsql.pgsql.cpu.usage_time",
            "delay": "0",
            "type": "18",
            "value_type": "0"
        },
        {
            "itemid": "44988",
            "name": "CPU utilization",
            "key_": "gcp.cloudsql.pgsql.cpu.utilization",
            "delay": "0",
            "type": "18",
            "value_type": "0"
        },
        {
            "itemid": "44879",
            "name": "DB engine state",
            "key_": "gcp.cloudsql.pgsql.db.state",
            "delay": "1m",
            "type": "19",
            "value_type": "3"
        },
        {
            "itemid": "44987",
            "name": "Disk bytes used",
            "key_": "gcp.cloudsql.pgsql.disk.bytes_used",
            "delay": "0",
            "type": "18",
            "value_type": "3"
        },
        {
            "itemid": "44986",
            "name": "Disk size",
            "key_": "gcp.cloudsql.pgsql.disk.quota",
            "delay": "0",
            "type": "18",
            "value_type": "3"
        },
        {
            "itemid": "44985",
            "name": "Disk read I/O",
            "key_": "gcp.cloudsql.pgsql.disk.read_ops_count",
            "delay": "0",
            "type": "18",
            "value_type": "3"
        },
        {
            "itemid": "44984",
            "name": "Disk utilization",
            "key_": "gcp.cloudsql.pgsql.disk.utilization",
            "delay": "0",
            "type": "18",
            "value_type": "0"
        },
        {
            "itemid": "44983",
            "name": "Disk write I/O",
            "key_": "gcp.cloudsql.pgsql.disk.write_ops_count",
            "delay": "0",
            "type": "18",
            "value_type": "3"
        },
        {
            "itemid": "44880",
            "name": "Instance state",
            "key_": "gcp.cloudsql.pgsql.inst.state",
            "delay": "1m",
            "type": "19",
            "value_type": "3"
        },
        {
            "itemid": "44982",
            "name": "Memory size",
            "key_": "gcp.cloudsql.pgsql.memory.quota",
            "delay": "0",
            "type": "18",
            "value_type": "3"
        },
        {
            "itemid": "44981",
            "name": "Memory used by DB engine",
            "key_": "gcp.cloudsql.pgsql.memory.total_usage",
            "delay": "0",
            "type": "18",
            "value_type": "3"
        },
        {
            "itemid": "44980",
            "name": "Memory usage",
            "key_": "gcp.cloudsql.pgsql.memory.usage",
            "delay": "0",
            "type": "18",
            "value_type": "3"
        },
        {
            "itemid": "44977",
            "name": "Memory utilization",
            "key_": "gcp.cloudsql.pgsql.memory.utilization",
            "delay": "0",
            "type": "18",
            "value_type": "0"
        },
        {
            "itemid": "44878",
            "name": "Metrics get",
            "key_": "gcp.cloudsql.pgsql.metrics.get",
            "delay": "{$GCP.TIME.WINDOW}",
            "type": "21",
            "value_type": "4"
        },
        {
            "itemid": "44978",
            "name": "Network: Received bytes",
            "key_": "gcp.cloudsql.pgsql.network.received_bytes_count",
            "delay": "0",
            "type": "18",
            "value_type": "3"
        },
        {
            "itemid": "44976",
            "name": "Network: Sent bytes",
            "key_": "gcp.cloudsql.pgsql.network.sent_bytes_count",
            "delay": "0",
            "type": "18",
            "value_type": "3"
        },
        {
            "itemid": "44975",
            "name": "Connections",
            "key_": "gcp.cloudsql.pgsql.num_backends",
            "delay": "0",
            "type": "18",
            "value_type": "3"
        },
        {
            "itemid": "44974",
            "name": "Oldest prepared transaction age",
            "key_": "gcp.cloudsql.pgsql.oldest_transaction.prepared",
            "delay": "0",
            "type": "18",
            "value_type": "3"
        },
        {
            "itemid": "44973",
            "name": "Oldest replica transaction age",
            "key_": "gcp.cloudsql.pgsql.oldest_transaction.replica",
            "delay": "0",
            "type": "18",
            "value_type": "3"
        },
        {
            "itemid": "44972",
            "name": "Oldest replication slot transaction age",
            "key_": "gcp.cloudsql.pgsql.oldest_transaction.replication_slot",
            "delay": "0",
            "type": "18",
            "value_type": "3"
        },
        {
            "itemid": "44971",
            "name": "Oldest running transaction age",
            "key_": "gcp.cloudsql.pgsql.oldest_transaction.running",
            "delay": "0",
            "type": "18",
            "value_type": "3"
        },
        {
            "itemid": "44970",
            "name": "Data written to temporary",
            "key_": "gcp.cloudsql.pgsql.temp_bytes_written_count",
            "delay": "0",
            "type": "18",
            "value_type": "3"
        },
        {
            "itemid": "44969",
            "name": "Temporary files used for writing data",
            "key_": "gcp.cloudsql.pgsql.temp_files_written_count",
            "delay": "0",
            "type": "18",
            "value_type": "3"
        },
        {
            "itemid": "44968",
            "name": "Assigned transactions",
            "key_": "gcp.cloudsql.pgsql.transaction_id_count_assigned",
            "delay": "0",
            "type": "18",
            "value_type": "3"
        },
        {
            "itemid": "44967",
            "name": "Frozen transactions",
            "key_": "gcp.cloudsql.pgsql.transaction_id_count_frozen",
            "delay": "0",
            "type": "18",
            "value_type": "3"
        },
        {
            "itemid": "44989",
            "name": "Transaction ID utilization",
            "key_": "gcp.cloudsql.pgsql.transaction_id_utilization",
            "delay": "0",
            "type": "18",
            "value_type": "0"
        }
    ]
}